version_inc/__init__.py
version_inc/__main__.py
version_inc/terminal_formatting.py
version_inc-2025.9.3.dist-info/METADATA
version_inc-2025.9.3.dist-info/WHEEL
version_inc-2025.9.3.dist-info/entry_points.txt
version_inc-2025.9.3.dist-info/licenses/LICENSE.txt
version_inc-2025.9.3.dist-info/RECORD
