Metadata-Version: 2.4
Name: Version-Inc
Version: 2025.9.3
Summary: A lightweight tool for incrementing version numbers in files
Author: Günthner
License-File: LICENSE.txt
Keywords: Versions
Classifier: Environment :: Console
Classifier: License :: OSI Approved :: MIT License
Classifier: Operating System :: OS Independent
Classifier: Programming Language :: Python :: 3
Requires-Python: >=3.8
